[["splice",["root"],[[1528,0,"{\"code\":0,\"indent\":24,\"parameters\":[]}","{\"code\":412,\"indent\":23,\"parameters\":[]}","{\"code\":0,\"indent\":23,\"parameters\":[]}","{\"code\":412,\"indent\":22,\"parameters\":[]}","{\"code\":0,\"indent\":22,\"parameters\":[]}","{\"code\":412,\"indent\":21,\"parameters\":[]}","{\"code\":0,\"indent\":21,\"parameters\":[]}","{\"code\":412,\"indent\":20,\"parameters\":[]}","{\"code\":0,\"indent\":20,\"parameters\":[]}","{\"code\":412,\"indent\":19,\"parameters\":[]}","{\"code\":0,\"indent\":19,\"parameters\":[]}","{\"code\":412,\"indent\":18,\"parameters\":[]}","{\"code\":0,\"indent\":18,\"parameters\":[]}","{\"code\":412,\"indent\":17,\"parameters\":[]}","{\"code\":0,\"indent\":17,\"parameters\":[]}","{\"code\":412,\"indent\":16,\"parameters\":[]}","{\"code\":0,\"indent\":16,\"parameters\":[]}","{\"code\":412,\"indent\":15,\"parameters\":[]}","{\"code\":0,\"indent\":15,\"parameters\":[]}","{\"code\":412,\"indent\":14,\"parameters\":[]}","{\"code\":0,\"indent\":14,\"parameters\":[]}","{\"code\":412,\"indent\":13,\"parameters\":[]}","{\"code\":0,\"indent\":13,\"parameters\":[]}","{\"code\":412,\"indent\":12,\"parameters\":[]}","{\"code\":0,\"indent\":12,\"parameters\":[]}","{\"code\":412,\"indent\":11,\"parameters\":[]}","{\"code\":0,\"indent\":11,\"parameters\":[]}","{\"code\":412,\"indent\":10,\"parameters\":[]}","{\"code\":0,\"indent\":10,\"parameters\":[]}","{\"code\":412,\"indent\":9,\"parameters\":[]}","{\"code\":0,\"indent\":9,\"parameters\":[]}","{\"code\":412,\"indent\":8,\"parameters\":[]}","{\"code\":0,\"indent\":8,\"parameters\":[]}","{\"code\":412,\"indent\":7,\"parameters\":[]}","{\"code\":0,\"indent\":7,\"parameters\":[]}","{\"code\":412,\"indent\":6,\"parameters\":[]}","{\"code\":0,\"indent\":6,\"parameters\":[]}","{\"code\":412,\"indent\":5,\"parameters\":[]}","{\"code\":0,\"indent\":5,\"parameters\":[]}","{\"code\":412,\"indent\":4,\"parameters\":[]}","{\"code\":0,\"indent\":4,\"parameters\":[]}","{\"code\":412,\"indent\":3,\"parameters\":[]}","{\"code\":0,\"indent\":3,\"parameters\":[]}","{\"code\":412,\"indent\":2,\"parameters\":[]}","{\"code\":0,\"indent\":2,\"parameters\":[]}","{\"code\":412,\"indent\":1,\"parameters\":[]}","{\"code\":0,\"indent\":1,\"parameters\":[]}","{\"code\":412,\"indent\":0,\"parameters\":[]}","{\"code\":111,\"indent\":0,\"parameters\":[4,48,6,1]}","{\"code\":121,\"indent\":1,\"parameters\":[1799,1799,0]}","{\"code\":0,\"indent\":1,\"parameters\":[]}","{\"code\":411,\"indent\":0,\"parameters\":[]}","{\"code\":111,\"indent\":1,\"parameters\":[4,48,6,14]}","{\"code\":121,\"indent\":2,\"parameters\":[1799,1799,0]}","{\"code\":0,\"indent\":2,\"parameters\":[]}","{\"code\":411,\"indent\":1,\"parameters\":[]}","{\"code\":111,\"indent\":2,\"parameters\":[4,48,6,17]}","{\"code\":121,\"indent\":3,\"parameters\":[1799,1799,0]}","{\"code\":0,\"indent\":3,\"parameters\":[]}","{\"code\":411,\"indent\":2,\"parameters\":[]}","{\"code\":111,\"indent\":3,\"parameters\":[4,48,6,18]}","{\"code\":121,\"indent\":4,\"parameters\":[1799,1799,0]}","{\"code\":0,\"indent\":4,\"parameters\":[]}","{\"code\":411,\"indent\":3,\"parameters\":[]}","{\"code\":111,\"indent\":4,\"parameters\":[4,48,6,19]}","{\"code\":121,\"indent\":5,\"parameters\":[1799,1799,0]}","{\"code\":0,\"indent\":5,\"parameters\":[]}","{\"code\":411,\"indent\":4,\"parameters\":[]}","{\"code\":111,\"indent\":5,\"parameters\":[4,48,6,37]}","{\"code\":121,\"indent\":6,\"parameters\":[1799,1799,0]}","{\"code\":0,\"indent\":6,\"parameters\":[]}","{\"code\":411,\"indent\":5,\"parameters\":[]}","{\"code\":111,\"indent\":6,\"parameters\":[4,48,6,25]}","{\"code\":121,\"indent\":7,\"parameters\":[1799,1799,0]}","{\"code\":0,\"indent\":7,\"parameters\":[]}","{\"code\":411,\"indent\":6,\"parameters\":[]}","{\"code\":111,\"indent\":7,\"parameters\":[4,48,6,8]}","{\"code\":121,\"indent\":8,\"parameters\":[1799,1799,0]}","{\"code\":0,\"indent\":8,\"parameters\":[]}","{\"code\":411,\"indent\":7,\"parameters\":[]}","{\"code\":111,\"indent\":8,\"parameters\":[4,48,6,75]}","{\"code\":121,\"indent\":9,\"parameters\":[1799,1799,0]}","{\"code\":0,\"indent\":9,\"parameters\":[]}","{\"code\":411,\"indent\":8,\"parameters\":[]}","{\"code\":111,\"indent\":9,\"parameters\":[4,48,6,118]}","{\"code\":121,\"indent\":10,\"parameters\":[1799,1799,0]}","{\"code\":0,\"indent\":10,\"parameters\":[]}","{\"code\":411,\"indent\":9,\"parameters\":[]}","{\"code\":111,\"indent\":10,\"parameters\":[4,48,6,144]}","{\"code\":121,\"indent\":11,\"parameters\":[1799,1799,0]}","{\"code\":0,\"indent\":11,\"parameters\":[]}","{\"code\":411,\"indent\":10,\"parameters\":[]}","{\"code\":111,\"indent\":11,\"parameters\":[4,48,6,72]}","{\"code\":121,\"indent\":12,\"parameters\":[1799,1799,0]}","{\"code\":0,\"indent\":12,\"parameters\":[]}","{\"code\":411,\"indent\":11,\"parameters\":[]}","{\"code\":111,\"indent\":12,\"parameters\":[4,48,6,160]}","{\"code\":121,\"indent\":13,\"parameters\":[1799,1799,0]}","{\"code\":0,\"indent\":13,\"parameters\":[]}","{\"code\":411,\"indent\":12,\"parameters\":[]}","{\"code\":111,\"indent\":13,\"parameters\":[4,48,6,166]}","{\"code\":121,\"indent\":14,\"parameters\":[1799,1799,0]}","{\"code\":0,\"indent\":14,\"parameters\":[]}","{\"code\":411,\"indent\":13,\"parameters\":[]}","{\"code\":111,\"indent\":14,\"parameters\":[4,48,6,212]}","{\"code\":121,\"indent\":15,\"parameters\":[1799,1799,0]}","{\"code\":0,\"indent\":15,\"parameters\":[]}","{\"code\":411,\"indent\":14,\"parameters\":[]}","{\"code\":111,\"indent\":15,\"parameters\":[4,48,6,149]}","{\"code\":121,\"indent\":16,\"parameters\":[1799,1799,0]}","{\"code\":0,\"indent\":16,\"parameters\":[]}","{\"code\":411,\"indent\":15,\"parameters\":[]}","{\"code\":111,\"indent\":16,\"parameters\":[4,48,6,148]}","{\"code\":121,\"indent\":17,\"parameters\":[1799,1799,0]}","{\"code\":0,\"indent\":17,\"parameters\":[]}","{\"code\":411,\"indent\":16,\"parameters\":[]}","{\"code\":111,\"indent\":17,\"parameters\":[4,48,6,145]}","{\"code\":121,\"indent\":18,\"parameters\":[1799,1799,0]}","{\"code\":0,\"indent\":18,\"parameters\":[]}","{\"code\":411,\"indent\":17,\"parameters\":[]}","{\"code\":111,\"indent\":18,\"parameters\":[4,48,6,140]}","{\"code\":121,\"indent\":19,\"parameters\":[1799,1799,0]}","{\"code\":0,\"indent\":19,\"parameters\":[]}","{\"code\":411,\"indent\":18,\"parameters\":[]}","{\"code\":111,\"indent\":19,\"parameters\":[4,48,6,279]}","{\"code\":121,\"indent\":20,\"parameters\":[1799,1799,0]}","{\"code\":0,\"indent\":20,\"parameters\":[]}","{\"code\":411,\"indent\":19,\"parameters\":[]}","{\"code\":111,\"indent\":20,\"parameters\":[4,48,6,50]}","{\"code\":121,\"indent\":21,\"parameters\":[1799,1799,0]}","{\"code\":0,\"indent\":21,\"parameters\":[]}","{\"code\":411,\"indent\":20,\"parameters\":[]}","{\"code\":111,\"indent\":21,\"parameters\":[4,48,6,113]}","{\"code\":121,\"indent\":22,\"parameters\":[1799,1799,0]}","{\"code\":0,\"indent\":22,\"parameters\":[]}","{\"code\":411,\"indent\":21,\"parameters\":[]}","{\"code\":111,\"indent\":22,\"parameters\":[4,48,6,73]}","{\"code\":121,\"indent\":23,\"parameters\":[1799,1799,0]}","{\"code\":0,\"indent\":23,\"parameters\":[]}","{\"code\":411,\"indent\":22,\"parameters\":[]}","{\"code\":111,\"indent\":23,\"parameters\":[0,1857,0]}","{\"code\":121,\"indent\":24,\"parameters\":[1799,1799,0]}","{\"code\":0,\"indent\":24,\"parameters\":[]}","{\"code\":411,\"indent\":23,\"parameters\":[]}","{\"code\":121,\"indent\":24,\"parameters\":[1799,1799,1]}"]]]]